litestar_saq/__init__.py
litestar_saq/__metadata__.py
litestar_saq/_typing.py
litestar_saq/base.py
litestar_saq/cli.py
litestar_saq/config.py
litestar_saq/controllers.py
litestar_saq/decorators.py
litestar_saq/exceptions.py
litestar_saq/hooks.py
litestar_saq/instrumentation.py
litestar_saq/plugin.py
litestar_saq/py.typed
litestar_saq/typing.py
litestar_saq-0.6.4.dist-info/METADATA
litestar_saq-0.6.4.dist-info/WHEEL
litestar_saq-0.6.4.dist-info/licenses/LICENSE
litestar_saq-0.6.4.dist-info/RECORD
