Metadata-Version: 2.4
Name: litestar-saq
Version: 0.6.4
Summary: Litestar integration for SAQ
Project-URL: Changelog, https://cofin.github.io/litesatr-saq/latest/changelog
Project-URL: Discord, https://discord.gg/X3FJqy8d2j
Project-URL: Documentation, https://cofin.github.io/litesatr-saq/latest/
Project-URL: Homepage, https://cofin.github.io/litesatr-saq/latest/
Project-URL: Issue, https://github.com/cofin/litestar-saq/issues/
Project-URL: Source, https://github.com/cofin/litestar-saq
Author-email: Cody Fincher <cody.fincher@gmail.com>
License: MIT
License-File: LICENSE
Keywords: litestar,saq
Classifier: Development Status :: 3 - Alpha
Classifier: Environment :: Web Environment
Classifier: License :: OSI Approved :: MIT License
Classifier: Natural Language :: English
Classifier: Operating System :: OS Independent
Classifier: Programming Language :: Python
Classifier: Programming Language :: Python :: 3.9
Classifier: Programming Language :: Python :: 3.10
Classifier: Programming Language :: Python :: 3.11
Classifier: Programming Language :: Python :: 3.12
Classifier: Programming Language :: Python :: 3.13
Classifier: Topic :: Software Development
Classifier: Typing :: Typed
Requires-Python: >=3.9
Requires-Dist: litestar>=2.0.1
Requires-Dist: saq>=0.26.0
Provides-Extra: hiredis
Requires-Dist: hiredis; extra == 'hiredis'
Provides-Extra: otel
Requires-Dist: opentelemetry-api; extra == 'otel'
Requires-Dist: opentelemetry-sdk; extra == 'otel'
Provides-Extra: psycopg
Requires-Dist: psycopg[binary,pool]; extra == 'psycopg'
